heartdisease_model/VERSION
heartdisease_model/__init__.py
heartdisease_model/config.yml
heartdisease_model/pipeline.py
heartdisease_model/predict.py
heartdisease_model/train_pipeline.py
heartdisease_model/config/__init__.py
heartdisease_model/config/core.py
heartdisease_model/datasets/test.csv
heartdisease_model/datasets/train.csv
heartdisease_model/processing/__init__.py
heartdisease_model/processing/data_manager.py
heartdisease_model/processing/features.py
heartdisease_model/processing/validation.py
heartdisease_model/trained_models/heartdisease_model_output_v0.0.8.pkl
heartdisease_model-0.0.8.dist-info/METADATA
heartdisease_model-0.0.8.dist-info/WHEEL
heartdisease_model-0.0.8.dist-info/top_level.txt
heartdisease_model-0.0.8.dist-info/RECORD
